pykg/__init__.py
pykg/providers/__init__.py
pykg/providers/gcp/__init__.py
pykg/providers/gcp/operators/dataproc.py
pykg-0.1.1.dist-info/LICENSE
pykg-0.1.1.dist-info/WHEEL
pykg-0.1.1.dist-info/METADATA
pykg-0.1.1.dist-info/RECORD
